ejtrader/__init__.py
ejtrader/invest/__init__.py
ejtrader/invest/bonds.py
ejtrader/invest/certificates.py
ejtrader/invest/commodities.py
ejtrader/invest/crypto.py
ejtrader/invest/currency_crosses.py
ejtrader/invest/etfs.py
ejtrader/invest/funds.py
ejtrader/invest/indices.py
ejtrader/invest/news.py
ejtrader/invest/search.py
ejtrader/invest/stocks.py
ejtrader/invest/technical.py
ejtrader/invest/data/__init__.py
ejtrader/invest/data/bonds_data.py
ejtrader/invest/data/certificates_data.py
ejtrader/invest/data/commodities_data.py
ejtrader/invest/data/crypto_data.py
ejtrader/invest/data/currency_crosses_data.py
ejtrader/invest/data/etfs_data.py
ejtrader/invest/data/funds_data.py
ejtrader/invest/data/indices_data.py
ejtrader/invest/data/stocks_data.py
ejtrader/invest/resources/bonds.csv
ejtrader/invest/resources/certificates.csv
ejtrader/invest/resources/commodities.csv
ejtrader/invest/resources/cryptos.csv
ejtrader/invest/resources/currency_crosses.csv
ejtrader/invest/resources/etfs.csv
ejtrader/invest/resources/funds.csv
ejtrader/invest/resources/indices.csv
ejtrader/invest/resources/stocks.csv
ejtrader/invest/utils/__init__.py
ejtrader/invest/utils/constant.py
ejtrader/invest/utils/data.py
ejtrader/invest/utils/extra.py
ejtrader/invest/utils/search_obj.py
ejtrader/iqoptions/__init__.py
ejtrader/iqoptions/iq.py
ejtrader/metaquote/__init__.py
ejtrader/metaquote/platafrom.py
ejtrader/metaquote/helpers/__init__.py
ejtrader/metaquote/helpers/utils.py
ejtrader/technicalslocal/__init__.py
ejtrader/technicalslocal/charts.py
ejtrader/technicalslocal/taindicators.py
ejtrader/technicalslocal/candlestick/__init__.py
ejtrader/technicalslocal/candlestick/candlestick.py
tests/__init__.py
tests/requirements.txt
tests/test_ejtrader.py
tests/test_ejtrader_errors.py
ejtrader-3.0.4.dist-info/LICENSE
ejtrader-3.0.4.dist-info/METADATA
ejtrader-3.0.4.dist-info/WHEEL
ejtrader-3.0.4.dist-info/top_level.txt
ejtrader-3.0.4.dist-info/RECORD
